{"Deep Learning Setup": [1, "/categories/deep-learning-setup.html", {"posts": [{"date": "01/21/2018", "isodate": "2018-01-21T12:06:09+00:00", "title": "Deep Learning Setup", "url": "/posts/second-post.html"}]}], "Hardware": [1, "/categories/hardware.html", {"posts": [{"date": "01/21/2018", "isodate": "2018-01-21T12:06:09+00:00", "title": "Audio Drivers Installion", "url": "/posts/first-post.html"}]}], "Installation": [2, "/categories/installation.html", {"posts": [{"date": "01/21/2018", "isodate": "2018-01-21T12:06:09+00:00", "title": "Deep Learning Setup", "url": "/posts/second-post.html"}, {"date": "01/21/2018", "isodate": "2018-01-21T12:06:09+00:00", "title": "Audio Drivers Installion", "url": "/posts/first-post.html"}]}], "Leet Code": [1, "/categories/leet-code.html", {"posts": [{"date": "01/21/2018", "isodate": "2018-01-21T12:06:09+00:00", "title": "Competitive Programming Trajectory", "url": "/posts/third-post.html"}]}], "Practice": [1, "/categories/practice.html", {"posts": [{"date": "01/21/2018", "isodate": "2018-01-21T12:06:09+00:00", "title": "Competitive Programming Trajectory", "url": "/posts/third-post.html"}]}]}